09_beq/reg.vhd
-- reg.vhd
library ieee;
use ieee.std_logic_1164.all;
use ieee.numeric_std.all; 

entity reg is
	port(
		clk		: in std_logic;
		rs1		: in std_logic_vector(4 downto 0);
		rs2		: in std_logic_vector(4 downto 0);
		rd		: in std_logic_vector(4 downto 0);
		we		: in std_logic;
		wdata	: in std_logic_vector(31 downto 0);
		rdata1	: out std_logic_vector(31 downto 0);
		rdata2	: out std_logic_vector(31 downto 0)
	);
end entity;

architecture rtl of reg is
    -- 1. レジスタ配列の宣言
	type reg_array is array(0 to 31) of std_logic_vector(31 downto 0);
	signal regs : reg_array := (others => (others => '0'));

begin
	-- 2. 書き込み処理（process + rising_edge）
	process(clk)
	begin
		if rising_edge(clk) then
			if we = '1' then
				regs(to_integer(unsigned(rd))) <= wdata;
			end if;
		end if;
	end process;
	-- 3. 読み出し処理（並行処理文でOK）
	rdata1 <= (others => '0') when rs1 = "00000" 
		else regs(to_integer(unsigned(rs1)));
	rdata2 <= (others => '0') when rs2 = "00000"
		else regs(to_integer(unsigned(rs2)));
end architecture;

03_reg/tb_reg.vhd
-- tb_reg.vhd
library ieee;
use ieee.std_logic_1164.all;

entity tb_reg is
end entity;

architecture sim of tb_reg is
	signal clk, we 					: std_logic;
	signal rs1, rs2, rd				: std_logic_vector(4 downto 0);
	signal wdata, rdata1, rdata2	: std_logic_vector(31 downto 0);
begin
	uut: entity work.reg 
		port map(
			clk   	=> clk,
			we		=> we,
			wdata	=> wdata,
			rdata1	=> rdata1,
			rdata2	=> rdata2,
			rs1		=> rs1,
			rs2		=> rs2,
			rd		=> rd
		);
	process
	begin
		clk <= '0'; wait for 5 ns;
    	clk <= '1'; wait for 5 ns;
	end process;
	-- テスト用プロセス
	process
	begin
		-- 1. レジスタ1に'1'を書き込む
		rd    <= "00001";
		wdata <= x"00000001";
		we    <= '1';
		wait for 10 ns;

		-- 2. 書き込み終わり
		we <= '0';

		-- 3. レジスタ1を読み出す
		rs1 <= "00001";
		wait for 10 ns;
		-- 1. x1に x"DEADBEEF" を書き込む
		rd <= "00001"; wdata <= x"DEADBEEF"; we <= '1';
		wait for 10 ns;

		-- 2. x2に x"12345678" を書き込む
		rd <= "00010"; wdata <= x"12345678"; we <= '1';
		wait for 10 ns;

		-- 3. x1とx2を同時に読み出す
		we  <= '0';
		rs1 <= "00001";
		rs2 <= "00010";
		wait for 10 ns;

		-- 4. x0に書き込もうとしても0のまま
		rd    <= "00000";
		wdata <= x"FFFFFFFF";
		we    <= '1';
		wait for 10 ns;

		we  <= '0';
		rs1 <= "00000";  -- x0を読み出す
		wait for 10 ns;

		wait;

	end process;
	

end architecture;

03_reg/wave.vcd
$date
  Mon Mar 30 19:37:43 2026
$end
$version
  GHDL v0
$end
$timescale
  1 fs
$end
$scope module standard $end
$upscope $end
$scope module std_logic_1164 $end
$upscope $end
$scope module numeric_std $end
$upscope $end
$scope module tb_reg $end
$var reg 1 ! clk $end
$var reg 1 " we $end
$var reg 5 # rs1[4:0] $end
$var reg 5 $ rs2[4:0] $end
$var reg 5 % rd[4:0] $end
$var reg 32 & wdata[31:0] $end
$var reg 32 ' rdata1[31:0] $end
$var reg 32 ( rdata2[31:0] $end
$scope module uut $end
$var reg 1 ) clk $end
$var reg 5 * rs1[4:0] $end
$var reg 5 + rs2[4:0] $end
$var reg 5 , rd[4:0] $end
$var reg 1 - we $end
$var reg 32 . wdata[31:0] $end
$var reg 32 / rdata1[31:0] $end
$var reg 32 0 rdata2[31:0] $end
$comment regs is not handled $end
$upscope $end
$upscope $end
$enddefinitions $end
#0
0!
1"
bUUUUU #
bUUUUU $
b00001 %
b00000000000000000000000000000001 &
b00000000000000000000000000000000 '
b00000000000000000000000000000000 (
0)
bUUUUU *
bUUUUU +
b00001 ,
1-
b00000000000000000000000000000001 .
b00000000000000000000000000000000 /
b00000000000000000000000000000000 0
#5000000
1!
1)
#10000000
0!
0"
b00001 #
b00000000000000000000000000000001 '
0)
b00001 *
0-
b00000000000000000000000000000001 /
#15000000
1!
1)
#20000000
0!
1"
b11011110101011011011111011101111 &
0)
1-
b11011110101011011011111011101111 .
#25000000
1!
b11011110101011011011111011101111 '
1)
b11011110101011011011111011101111 /
#30000000
0!
b00010 %
b00010010001101000101011001111000 &
0)
b00010 ,
b00010010001101000101011001111000 .
#35000000
1!
1)
#40000000
0!
0"
b00010 $
b00010010001101000101011001111000 (
0)
b00010 +
0-
b00010010001101000101011001111000 0
#45000000
1!
1)
#50000000
0!
1"
b00000 %
b11111111111111111111111111111111 &
0)
b00000 ,
1-
b11111111111111111111111111111111 .
#55000000
1!
1)
#60000000
0!
0"
b00000 #
b00000000000000000000000000000000 '
0)
b00000 *
0-
b00000000000000000000000000000000 /
