08_dmem/dmem.vhd
-- dmem.vhd
library ieee;
use ieee.std_logic_1164.all;
use ieee.numeric_std.all;

entity dmem is
	port (
		clk		: in std_logic;
		we		: in std_logic;
		addr	: in std_logic_vector(31 downto 0);
		wdata	: in std_logic_vector(31 downto 0);
		rdata	: out std_logic_vector(31 downto 0)
	);
end entity;

architecture rtl of dmem is
    type mem_array is array(0 to 255) of std_logic_vector(31 downto 0);
    signal mem      : mem_array := (others => (others => '0'));
    signal addr_int : integer := 0;  -- range制約を外す
begin
    process(addr)
    begin
        if is_x(addr) then
            addr_int <= 0;
        elsif to_integer(unsigned(addr)) / 4 < 256 then
            addr_int <= to_integer(unsigned(addr)) / 4;
        else
            addr_int <= 0;
        end if;
    end process;

    rdata <= mem(addr_int);

    process(clk)
    begin
        if rising_edge(clk) then
            if we = '1' then
                mem(addr_int) <= wdata;
            end if;
        end if;
    end process;
end architecture;

08_dmem/imem.vhd
-- imem.vhd
library ieee;
use ieee.std_logic_1164.all;
use ieee.numeric_std.all;

entity imem is
	port (
		addr	: in std_logic_vector(31 downto 0);
		instr	: out std_logic_vector(31 downto 0)
	);
end entity;

architecture rtl of imem is
	type mem_array is array(0 to 15) of std_logic_vector(31 downto 0);
	constant mem : mem_array := (
		0 => x"00500093",  -- addi x1, x0, 5
		1 => x"00000013",  -- NOP
		2 => x"00102023",  -- sw x1, 0(x0)
		3 => x"00002103",  -- lw x2, 0(x0)
		others => x"00000000"
	);
begin
    instr <= mem(to_integer(unsigned(addr)) / 4)
        when to_integer(unsigned(addr)) / 4 < 16
        else x"00000000";
end architecture;

06_cpu/decoder.vhd
-- decoder.vhd
library ieee;
use ieee.std_logic_1164.all;
use ieee.numeric_std.all;

entity decoder is
	port (
		instr	: in std_logic_vector(31 downto 0);
		rs1		: out std_logic_vector(4 downto 0);
		rs2		: out std_logic_vector(4 downto 0);
		rd		: out std_logic_vector(4 downto 0);
		imm		: out std_logic_vector(31 downto 0);
		alu_op	: out std_logic_vector(3 downto 0);
		reg_we	: out std_logic;
		mem_we	: out std_logic
	);
end entity;

architecture rtl of decoder is
	signal opcode : std_logic_vector(6 downto 0);
begin
	rs1 <= instr(19 downto 15);
	rs2 <= instr(24 downto 20);
	rd  <= instr(11 downto  7);
	opcode <= instr(6 downto 0);
	process(instr)
	begin
		case instr(6 downto 0) is
			when "0110011" => -- R型（add）
				alu_op <= "0000";
				reg_we <= '1';
				mem_we <= '0';
				imm	<= (others => '0');
			when "0010011" => -- I型（addi）
				alu_op <= "0000";
				reg_we <= '1';
				mem_we <= '0';
				imm <= std_logic_vector(resize(signed(instr(31 downto 20)), 32));
			when others =>
				alu_op <= "0000";
				reg_we <= '0';
				mem_we <= '0';
				imm <= (others => '0');
		end case;
	end process;
end architecture;

08_dmem/alu.vhd
-- alu.vhd
library ieee;
use ieee.std_logic_1164.all;
use ieee.numeric_std.all; 

entity alu is
	port (
		op		: in std_logic_vector(3 downto 0);
		src_a	: in std_logic_vector(31 downto 0);
		src_b	: in std_logic_vector(31 downto 0);
		result	: out std_logic_vector(31 downto 0);
		zero	: out std_logic
	);
end entity;

architecture rtl of alu is
	signal result_i : std_logic_vector(31 downto 0);
begin
	process(op, src_a, src_b)
	begin
		case op is
			when "0000" => result_i <= std_logic_vector(signed(src_a) + signed(src_b));											-- ADD
			when "0001" => result_i <= std_logic_vector(signed(src_a) - signed(src_b));											-- SUB
			when "0010" => result_i <= src_a and src_b;																			-- AND
			when "0011" => result_i <= src_a or src_b;																			-- OR
			when "0100" => result_i <= src_a xor src_b; 																		-- XOR
			when "0101" => result_i <= std_logic_vector(shift_left(unsigned(src_a), to_integer(unsigned(src_b(4 downto 0)))));	-- SLL
			-- src_b(4 downto 0) → シフト量は下位5bitだけ使う（RISC-Vの仕様）
			when "0110" => result_i <= std_logic_vector(shift_right(unsigned(src_a), to_integer(unsigned(src_b(4 downto 0)))));	-- SRL
			when "0111" => result_i <= std_logic_vector(shift_right(signed(src_a), to_integer(unsigned(src_b(4 downto 0)))));	-- SRA
			when others => result_i <= (others => '0');
		end case;
	end process;
	result <= result_i;
	zero <= '1' when result_i = x"00000000" else '0';
end architecture;

09_beq/reg.vhd
-- reg.vhd
library ieee;
use ieee.std_logic_1164.all;
use ieee.numeric_std.all; 

entity reg is
	port(
		clk		: in std_logic;
		rs1		: in std_logic_vector(4 downto 0);
		rs2		: in std_logic_vector(4 downto 0);
		rd		: in std_logic_vector(4 downto 0);
		we		: in std_logic;
		wdata	: in std_logic_vector(31 downto 0);
		rdata1	: out std_logic_vector(31 downto 0);
		rdata2	: out std_logic_vector(31 downto 0)
	);
end entity;

architecture rtl of reg is
    -- 1. レジスタ配列の宣言
	type reg_array is array(0 to 31) of std_logic_vector(31 downto 0);
	signal regs : reg_array := (others => (others => '0'));

begin
	-- 2. 書き込み処理（process + rising_edge）
	process(clk)
	begin
		if rising_edge(clk) then
			if we = '1' then
				regs(to_integer(unsigned(rd))) <= wdata;
			end if;
		end if;
	end process;
	-- 3. 読み出し処理（並行処理文でOK）
	rdata1 <= (others => '0') when rs1 = "00000" 
		else regs(to_integer(unsigned(rs1)));
	rdata2 <= (others => '0') when rs2 = "00000"
		else regs(to_integer(unsigned(rs2)));
end architecture;

08_dmem/cpu_top.vhd
-- cpu_top.vhd
library ieee;
use ieee.std_logic_1164.all;
use ieee.numeric_std.all;

entity cpu_top is
	port (
		clk		: in std_logic;
		rst		: in std_logic;
		pc		: out std_logic_vector(31 downto 0)
	);
end entity;

architecture rtl of cpu_top is

    -- 内部信号（各モジュールをつなぐ配線）
    signal rs1_addr, rs2_addr, rd_addr	: std_logic_vector(4 downto 0);
    signal alu_op						: std_logic_vector(3 downto 0);
    signal imm, alu_src_a, alu_src_b	: std_logic_vector(31 downto 0);
    signal alu_result					: std_logic_vector(31 downto 0);
    signal rdata1, rdata2				: std_logic_vector(31 downto 0);
    signal reg_we, mem_we, zero			: std_logic;
	signal pc_reg						: std_logic_vector(31 downto 0) := (others => '0');
	signal instr						: std_logic_vector(31 downto 0);
	signal dmem_rdata					: std_logic_vector(31 downto 0);
	signal reg_wdata					: std_logic_vector(31 downto 0);
	signal reg_we_masked				: std_logic;
	signal mem_we_masked				: std_logic;

begin
	reg_we_masked <= reg_we and (not rst);
	mem_we_masked <= mem_we and (not rst);
	u_reg: entity work.reg
    port map(
        clk    => clk,
        rs1    => rs1_addr,
        rs2    => rs2_addr,
        rd     => rd_addr,
        we     => reg_we_masked,
        wdata => reg_wdata,
        rdata1 => rdata1,
        rdata2 => rdata2
    );
	u_alu: entity work.alu
	port map(
		op => alu_op,
		src_a => alu_src_a,
		src_b => alu_src_b,
		result => alu_result,
		zero => zero
	);
	u_decoder: entity work.decoder
	port map(
		instr => instr,
		rs1 => rs1_addr,
		rs2 => rs2_addr,
		rd => rd_addr,
		imm => imm,
		alu_op => alu_op,
		reg_we => reg_we,
		mem_we => mem_we
	);
	u_imem: entity work.imem
		port map(
			addr => pc_reg,
			instr => instr
		);
	u_dmem: entity work.dmem
		port map(
			clk   => clk,
			we    => mem_we_masked,
			addr  => alu_result,
			wdata => rdata2,
			rdata => dmem_rdata
		);
	alu_src_a <= rdata1;
	alu_src_b <= rdata2 when instr(6 downto 0) = "0110011"
		else imm;
	reg_wdata <= dmem_rdata when instr(6 downto 0) = "0000011" else alu_result;
	process(clk)
	begin
		if rising_edge(clk) then
			if rst = '1' then
				pc_reg <= (others => '0');  -- リセット
			else
				pc_reg <= std_logic_vector(unsigned(pc_reg) + 4);  -- 次のPC
			end if;
		end if;
	end process;

	pc <= pc_reg;  -- 出力に接続
end architecture;

08_dmem/tb_cpu_top.vhd
-- tb_cpu_top.vhd
library ieee;
use ieee.std_logic_1164.all;

entity tb_cpu_top is
end entity;

architecture sim of tb_cpu_top is
	signal clk		: std_logic;
	signal rst		: std_logic;
	signal instr	: std_logic_vector(31 downto 0);
	signal pc		: std_logic_vector(31 downto 0);
begin
	uut: entity work.cpu_top 
		port map(
			clk => clk,
			rst => rst,
			pc => pc
		);
	process
	begin
		rst <= '1'; wait for 20 ns;  -- 2クロック分リセット保持
		rst <= '0'; wait for 80 ns;
		wait;
	end process;
	process
	begin
		clk <= '0'; wait for 5 ns;
		clk <= '1'; wait for 5 ns;
	end process;
end architecture;

08_dmem/wave.vcd
$date
  Thu Apr  2 11:53:53 2026
$end
$version
  GHDL v0
$end
$timescale
  1 fs
$end
$scope module standard $end
$upscope $end
$scope module std_logic_1164 $end
$upscope $end
$scope module numeric_std $end
$upscope $end
$scope module tb_cpu_top $end
$var reg 1 ! clk $end
$var reg 1 " rst $end
$var reg 32 # instr[31:0] $end
$var reg 32 $ pc[31:0] $end
$scope module uut $end
$var reg 1 % clk $end
$var reg 1 & rst $end
$var reg 32 ' pc[31:0] $end
$var reg 5 ( rs1_addr[4:0] $end
$var reg 5 ) rs2_addr[4:0] $end
$var reg 5 * rd_addr[4:0] $end
$var reg 4 + alu_op[3:0] $end
$var reg 32 , imm[31:0] $end
$var reg 32 - alu_src_a[31:0] $end
$var reg 32 . alu_src_b[31:0] $end
$var reg 32 / alu_result[31:0] $end
$var reg 32 0 rdata1[31:0] $end
$var reg 32 1 rdata2[31:0] $end
$var reg 1 2 reg_we $end
$var reg 1 3 mem_we $end
$var reg 1 4 zero $end
$var reg 32 5 pc_reg[31:0] $end
$var reg 32 6 instr[31:0] $end
$var reg 32 7 dmem_rdata[31:0] $end
$var reg 32 8 reg_wdata[31:0] $end
$var reg 1 9 reg_we_masked $end
$var reg 1 : mem_we_masked $end
$scope module u_reg $end
$var reg 1 ; clk $end
$var reg 5 < rs1[4:0] $end
$var reg 5 = rs2[4:0] $end
$var reg 5 > rd[4:0] $end
$var reg 1 ? we $end
$var reg 32 @ wdata[31:0] $end
$var reg 32 A rdata1[31:0] $end
$var reg 32 B rdata2[31:0] $end
$comment regs is not handled $end
$upscope $end
$scope module u_alu $end
$var reg 4 C op[3:0] $end
$var reg 32 D src_a[31:0] $end
$var reg 32 E src_b[31:0] $end
$var reg 32 F result[31:0] $end
$var reg 1 G zero $end
$var reg 32 H result_i[31:0] $end
$upscope $end
$scope module u_decoder $end
$var reg 32 I instr[31:0] $end
$var reg 5 J rs1[4:0] $end
$var reg 5 K rs2[4:0] $end
$var reg 5 L rd[4:0] $end
$var reg 32 M imm[31:0] $end
$var reg 4 N alu_op[3:0] $end
$var reg 1 O reg_we $end
$var reg 1 P mem_we $end
$var reg 7 Q opcode[6:0] $end
$upscope $end
$scope module u_imem $end
$var reg 32 R addr[31:0] $end
$var reg 32 S instr[31:0] $end
$upscope $end
$scope module u_dmem $end
$var reg 1 T clk $end
$var reg 1 U we $end
$var reg 32 V addr[31:0] $end
$var reg 32 W wdata[31:0] $end
$var reg 32 X rdata[31:0] $end
$comment mem is not handled $end
$var integer 32 Y addr_int $end
$upscope $end
$upscope $end
$upscope $end
$enddefinitions $end
#0
0!
1"
bUUUUUUUUUUUUUUUUUUUUUUUUUUUUUUUU #
b00000000000000000000000000000000 $
0%
1&
b00000000000000000000000000000000 '
b00000 (
b00101 )
b00001 *
b0000 +
b00000000000000000000000000000101 ,
b00000000000000000000000000000000 -
b00000000000000000000000000000101 .
b00000000000000000000000000000101 /
b00000000000000000000000000000000 0
b00000000000000000000000000000000 1
12
03
04
b00000000000000000000000000000000 5
b00000000010100000000000010010011 6
b00000000000000000000000000000000 7
b00000000000000000000000000000101 8
09
0:
0;
b00000 <
b00101 =
b00001 >
0?
b00000000000000000000000000000101 @
b00000000000000000000000000000000 A
b00000000000000000000000000000000 B
b0000 C
b00000000000000000000000000000000 D
b00000000000000000000000000000101 E
b00000000000000000000000000000101 F
0G
b00000000000000000000000000000101 H
b00000000010100000000000010010011 I
b00000 J
b00101 K
b00001 L
b00000000000000000000000000000101 M
b0000 N
1O
0P
b0010011 Q
b00000000000000000000000000000000 R
b00000000010100000000000010010011 S
0T
0U
b00000000000000000000000000000101 V
b00000000000000000000000000000000 W
b00000000000000000000000000000000 X
b1 Y
#5000000
1!
1%
1;
1T
#10000000
0!
0%
0;
0T
#15000000
1!
1%
1;
1T
#20000000
0!
0"
0%
0&
19
0;
1?
0T
#25000000
1!
b00000000000000000000000000000100 $
1%
b00000000000000000000000000000100 '
b00000 )
b00000 *
b00000000000000000000000000000000 ,
b00000000000000000000000000000000 .
b00000000000000000000000000000000 /
14
b00000000000000000000000000000100 5
b00000000000000000000000000010011 6
b00000000000000000000000000000000 8
1;
b00000 =
b00000 >
b00000000000000000000000000000000 @
b00000000000000000000000000000000 E
b00000000000000000000000000000000 F
1G
b00000000000000000000000000000000 H
b00000000000000000000000000010011 I
b00000 K
b00000 L
b00000000000000000000000000000000 M
b00000000000000000000000000000100 R
b00000000000000000000000000010011 S
1T
b00000000000000000000000000000000 V
b0 Y
#30000000
0!
0%
0;
0T
#35000000
1!
b00000000000000000000000000001000 $
1%
b00000000000000000000000000001000 '
b00001 )
b00000000000000000000000000000101 1
02
13
b00000000000000000000000000001000 5
b00000000000100000010000000100011 6
09
1:
1;
b00001 =
0?
b00000000000000000000000000000101 B
b00000000000100000010000000100011 I
b00001 K
0O
1P
b0100011 Q
b00000000000000000000000000001000 R
b00000000000100000010000000100011 S
1T
1U
b00000000000000000000000000000101 W
#40000000
0!
0%
0;
0T
#45000000
1!
b00000000000000000000000000001100 $
1%
b00000000000000000000000000001100 '
b00000 )
b00010 *
b00000000000000000000000000000000 1
12
03
b00000000000000000000000000001100 5
b00000000000000000010000100000011 6
b00000000000000000000000000000101 7
b00000000000000000000000000000101 8
19
0:
1;
b00000 =
b00010 >
1?
b00000000000000000000000000000101 @
b00000000000000000000000000000000 B
b00000000000000000010000100000011 I
b00000 K
b00010 L
1O
0P
b0000011 Q
b00000000000000000000000000001100 R
b00000000000000000010000100000011 S
1T
0U
b00000000000000000000000000000000 W
b00000000000000000000000000000101 X
#50000000
0!
0%
0;
0T
#55000000
1!
b00000000000000000000000000010000 $
1%
b00000000000000000000000000010000 '
b00000 *
02
b00000000000000000000000000010000 5
b00000000000000000000000000000000 6
b00000000000000000000000000000000 8
09
1;
b00000 >
0?
b00000000000000000000000000000000 @
b00000000000000000000000000000000 I
b00000 L
0O
b0000000 Q
b00000000000000000000000000010000 R
b00000000000000000000000000000000 S
1T
#60000000
0!
0%
0;
0T
#65000000
1!
b00000000000000000000000000010100 $
1%
b00000000000000000000000000010100 '
b00000000000000000000000000010100 5
1;
b00000000000000000000000000010100 R
1T
#70000000
0!
0%
0;
0T
#75000000
1!
b00000000000000000000000000011000 $
1%
b00000000000000000000000000011000 '
b00000000000000000000000000011000 5
1;
b00000000000000000000000000011000 R
1T
#80000000
0!
0%
0;
0T
#85000000
1!
b00000000000000000000000000011100 $
1%
b00000000000000000000000000011100 '
b00000000000000000000000000011100 5
1;
b00000000000000000000000000011100 R
1T
#90000000
0!
0%
0;
0T
#95000000
1!
b00000000000000000000000000100000 $
1%
b00000000000000000000000000100000 '
b00000000000000000000000000100000 5
1;
b00000000000000000000000000100000 R
1T
#100000000
0!
0%
0;
0T
#105000000
1!
b00000000000000000000000000100100 $
1%
b00000000000000000000000000100100 '
b00000000000000000000000000100100 5
1;
b00000000000000000000000000100100 R
1T
#110000000
0!
0%
0;
0T
#115000000
1!
b00000000000000000000000000101000 $
1%
b00000000000000000000000000101000 '
b00000000000000000000000000101000 5
1;
b00000000000000000000000000101000 R
1T
#120000000
0!
0%
0;
0T
#125000000
1!
b00000000000000000000000000101100 $
1%
b00000000000000000000000000101100 '
b00000000000000000000000000101100 5
1;
b00000000000000000000000000101100 R
1T
#130000000
0!
0%
0;
0T
#135000000
1!
b00000000000000000000000000110000 $
1%
b00000000000000000000000000110000 '
b00000000000000000000000000110000 5
1;
b00000000000000000000000000110000 R
1T
#140000000
0!
0%
0;
0T
#145000000
1!
b00000000000000000000000000110100 $
1%
b00000000000000000000000000110100 '
b00000000000000000000000000110100 5
1;
b00000000000000000000000000110100 R
1T
#150000000
0!
0%
0;
0T
#155000000
1!
b00000000000000000000000000111000 $
1%
b00000000000000000000000000111000 '
b00000000000000000000000000111000 5
1;
b00000000000000000000000000111000 R
1T
#160000000
0!
0%
0;
0T
#165000000
1!
b00000000000000000000000000111100 $
1%
b00000000000000000000000000111100 '
b00000000000000000000000000111100 5
1;
b00000000000000000000000000111100 R
1T
#170000000
0!
0%
0;
0T
#175000000
1!
b00000000000000000000000001000000 $
1%
b00000000000000000000000001000000 '
b00000000000000000000000001000000 5
1;
b00000000000000000000000001000000 R
1T
#180000000
0!
0%
0;
0T
#185000000
1!
b00000000000000000000000001000100 $
1%
b00000000000000000000000001000100 '
b00000000000000000000000001000100 5
1;
b00000000000000000000000001000100 R
1T
#190000000
0!
0%
0;
0T
#195000000
1!
b00000000000000000000000001001000 $
1%
b00000000000000000000000001001000 '
b00000000000000000000000001001000 5
1;
b00000000000000000000000001001000 R
1T
