02_dff/dff.vhd
-- dff.vhd
library ieee;
use ieee.std_logic_1164.all;

entity dff is
	port (
		clk   	: in std_logic;
		d		: in std_logic;
		q		: out std_logic
	);
end entity;

architecture rtl of dff is
begin
    process(clk)
    begin
        if rising_edge(clk) then
            q <= d;  -- クロックの瞬間だけ反映
        end if;
    end process;
end architecture;

02_dff/tb_dff.vhd
-- tb_dff.vhd
library ieee;
use ieee.std_logic_1164.all;

entity tb_dff is

end entity;

architecture sim of tb_dff is
	signal clk, d, q : std_logic;
begin
	uut: entity work.dff
		port map (
			clk => clk,
			d => d,
			q => q
		);
	process
	begin
		clk <= '0'; wait for 5 ns;
    	clk <= '1'; wait for 5 ns;
	end process;
	process
	begin
		d <= '0'; wait for 3 ns;
		d <= '1'; wait for 3 ns;
		d <= '0'; wait for 3 ns;
	end process;
end architecture;

02_dff/wave.vcd
$date
  Mon Mar 30 19:08:21 2026
$end
$version
  GHDL v0
$end
$timescale
  1 fs
$end
$scope module standard $end
$upscope $end
$scope module std_logic_1164 $end
$upscope $end
$scope module tb_dff $end
$var reg 1 ! clk $end
$var reg 1 " d $end
$var reg 1 # q $end
$scope module uut $end
$var reg 1 $ clk $end
$var reg 1 % d $end
$var reg 1 & q $end
$upscope $end
$upscope $end
$enddefinitions $end
#0
0!
0"
U#
0$
0%
U&
#3000000
1"
1%
#5000000
1!
1#
1$
1&
#6000000
0"
0%
#10000000
0!
0$
#12000000
1"
1%
#15000000
1!
0"
0#
1$
0%
0&
#20000000
0!
0$
#21000000
1"
1%
#24000000
0"
0%
#25000000
1!
1$
#30000000
0!
1"
0$
1%
#33000000
0"
0%
#35000000
1!
1$
#39000000
1"
1%
#40000000
0!
0$
#42000000
0"
0%
#45000000
1!
1$
#48000000
1"
1%
#50000000
0!
0$
#51000000
0"
0%
#55000000
1!
1$
#57000000
1"
1%
#60000000
0!
0"
0$
0%
#65000000
1!
1$
#66000000
1"
1%
#69000000
0"
0%
#70000000
0!
0$
#75000000
1!
1"
1#
1$
1%
1&
#78000000
0"
0%
#80000000
0!
0$
#84000000
1"
1%
#85000000
1!
1$
#87000000
0"
0%
#90000000
0!
0$
#93000000
1"
1%
#95000000
1!
1$
#96000000
0"
0%
#100000000
0!
0$
#102000000
1"
1%
#105000000
1!
0"
0#
1$
0%
0&
#110000000
0!
0$
#111000000
1"
1%
#114000000
0"
0%
#115000000
1!
1$
#120000000
0!
1"
0$
1%
#123000000
0"
0%
#125000000
1!
1$
#129000000
1"
1%
#130000000
0!
0$
#132000000
0"
0%
#135000000
1!
1$
#138000000
1"
1%
#140000000
0!
0$
#141000000
0"
0%
#145000000
1!
1$
#147000000
1"
1%
#150000000
0!
0"
0$
0%
#155000000
1!
1$
#156000000
1"
1%
#159000000
0"
0%
#160000000
0!
0$
#165000000
1!
1"
1#
1$
1%
1&
#168000000
0"
0%
#170000000
0!
0$
#174000000
1"
1%
#175000000
1!
1$
#177000000
0"
0%
#180000000
0!
0$
#183000000
1"
1%
#185000000
1!
1$
#186000000
0"
0%
#190000000
0!
0$
#192000000
1"
1%
#195000000
1!
0"
0#
1$
0%
0&
