06_cpu/decoder.vhd
-- decoder.vhd
library ieee;
use ieee.std_logic_1164.all;
use ieee.numeric_std.all;

entity decoder is
	port (
		instr	: in std_logic_vector(31 downto 0);
		rs1		: out std_logic_vector(4 downto 0);
		rs2		: out std_logic_vector(4 downto 0);
		rd		: out std_logic_vector(4 downto 0);
		imm		: out std_logic_vector(31 downto 0);
		alu_op	: out std_logic_vector(3 downto 0);
		reg_we	: out std_logic;
		mem_we	: out std_logic
	);
end entity;

architecture rtl of decoder is
	signal opcode : std_logic_vector(6 downto 0);
begin
	rs1 <= instr(19 downto 15);
	rs2 <= instr(24 downto 20);
	rd  <= instr(11 downto  7);
	opcode <= instr(6 downto 0);
	process(instr)
	begin
		case instr(6 downto 0) is
			when "0110011" => -- R型（add）
				alu_op <= "0000";
				reg_we <= '1';
				mem_we <= '0';
				imm	<= (others => '0');
			when "0010011" => -- I型（addi）
				alu_op <= "0000";
				reg_we <= '1';
				mem_we <= '0';
				imm <= std_logic_vector(resize(signed(instr(31 downto 20)), 32));
			when others =>
				alu_op <= "0000";
				reg_we <= '0';
				mem_we <= '0';
				imm <= (others => '0');
		end case;
	end process;
end architecture;

06_cpu/alu.vhd
-- alu.vhd
library ieee;
use ieee.std_logic_1164.all;
use ieee.numeric_std.all; 

entity alu is
	port (
		op		: in std_logic_vector(3 downto 0);
		src_a	: in std_logic_vector(31 downto 0);
		src_b	: in std_logic_vector(31 downto 0);
		result	: out std_logic_vector(31 downto 0);
		zero	: out std_logic
	);
end entity;

architecture rtl of alu is
	signal result_i : std_logic_vector(31 downto 0);
begin
	process(op, src_a, src_b)
	begin
		case op is
			when "0000" => result_i <= std_logic_vector(signed(src_a) + signed(src_b));											-- ADD
			when "0001" => result_i <= std_logic_vector(signed(src_a) - signed(src_b));											-- SUB
			when "0010" => result_i <= src_a and src_b;																			-- AND
			when "0011" => result_i <= src_a or src_b;																			-- OR
			when "0100" => result_i <= src_a xor src_b; 																			-- XOR
			when "0101" => result_i <= std_logic_vector(shift_left(unsigned(src_a), to_integer(unsigned(src_b(4 downto 0)))));	-- SLL
			-- src_b(4 downto 0) → シフト量は下位5bitだけ使う（RISC-Vの仕様）
			when "0110" => result_i <= std_logic_vector(shift_right(unsigned(src_a), to_integer(unsigned(src_b(4 downto 0)))));	-- SRL
			when "0111" => result_i <= std_logic_vector(shift_right(signed(src_a), to_integer(unsigned(src_b(4 downto 0)))));		-- SRA
			when others => result <= (others => '0');
		end case;
	end process;
	result <= result_i;
	zero <= '1' when result_i = x"00000000" else '0';
end architecture;

09_beq/reg.vhd
-- reg.vhd
library ieee;
use ieee.std_logic_1164.all;
use ieee.numeric_std.all; 

entity reg is
	port(
		clk		: in std_logic;
		rs1		: in std_logic_vector(4 downto 0);
		rs2		: in std_logic_vector(4 downto 0);
		rd		: in std_logic_vector(4 downto 0);
		we		: in std_logic;
		wdata	: in std_logic_vector(31 downto 0);
		rdata1	: out std_logic_vector(31 downto 0);
		rdata2	: out std_logic_vector(31 downto 0)
	);
end entity;

architecture rtl of reg is
    -- 1. レジスタ配列の宣言
	type reg_array is array(0 to 31) of std_logic_vector(31 downto 0);
	signal regs : reg_array := (others => (others => '0'));

begin
	-- 2. 書き込み処理（process + rising_edge）
	process(clk)
	begin
		if rising_edge(clk) then
			if we = '1' then
				regs(to_integer(unsigned(rd))) <= wdata;
			end if;
		end if;
	end process;
	-- 3. 読み出し処理（並行処理文でOK）
	rdata1 <= (others => '0') when rs1 = "00000" 
		else regs(to_integer(unsigned(rs1)));
	rdata2 <= (others => '0') when rs2 = "00000"
		else regs(to_integer(unsigned(rs2)));
end architecture;

06_cpu/cpu_top.vhd
-- cpu_top.vhd
library ieee;
use ieee.std_logic_1164.all;
use ieee.numeric_std.all;

entity cpu_top is
	port (
		clk		: in std_logic;
		rst		: in std_logic;
		instr	: in std_logic_vector(31 downto 0);
		pc		: out std_logic_vector(31 downto 0)
	);
end entity;

architecture rtl of cpu_top is

    -- 内部信号（各モジュールをつなぐ配線）
    signal rs1_addr, rs2_addr, rd_addr	: std_logic_vector(4 downto 0);
    signal alu_op						: std_logic_vector(3 downto 0);
    signal imm, alu_src_a, alu_src_b	: std_logic_vector(31 downto 0);
    signal alu_result					: std_logic_vector(31 downto 0);
    signal rdata1, rdata2				: std_logic_vector(31 downto 0);
    signal reg_we, mem_we, zero			: std_logic;
	signal pc_reg						: std_logic_vector(31 downto 0) := (others => '0');

begin
	u_reg: entity work.reg
    port map(
        clk    => clk,
        rs1    => rs1_addr,
        rs2    => rs2_addr,
        rd     => rd_addr,
        we     => reg_we,
        wdata  => alu_result,  -- ALUの結果をレジスタに書き込む
        rdata1 => rdata1,
        rdata2 => rdata2
    );
	u_alu: entity work.alu
	port map(
		op => alu_op,
		src_a => alu_src_a,
		src_b => alu_src_b,
		result => alu_result,
		zero => zero
	);
	u_decoder: entity work.decoder
	port map(
		instr => instr,
		rs1 => rs1_addr,
		rs2 => rs2_addr,
		rd => rd_addr,
		imm => imm,
		alu_op => alu_op,
		reg_we => reg_we,
		mem_we => mem_we
	);
	alu_src_a <= rdata1;
	alu_src_b <= rdata2 when instr(6 downto 0) = "0110011"
		else imm;
	process(clk)
	begin
		if rising_edge(clk) then
			if rst = '1' then
				pc_reg <= (others => '0');  -- リセット
			else
				pc_reg <= std_logic_vector(unsigned(pc_reg) + 4);  -- 次のPC
			end if;
		end if;
	end process;

	pc <= pc_reg;  -- 出力に接続
end architecture;

06_cpu/tb_cpu_top.vhd
-- tb_cpu_top.vhd
library ieee;
use ieee.std_logic_1164.all;

entity tb_cpu_top is
end entity;

architecture sim of tb_cpu_top is
	signal clk		: std_logic;
	signal rst		: std_logic;
	signal instr	: std_logic_vector(31 downto 0);
	signal pc		: std_logic_vector(31 downto 0);
begin
	uut: entity work.cpu_top 
		port map(
			clk => clk,
			rst => rst,
			instr => instr,
			pc => pc
		);
	process
	begin
		rst <= '1'; wait for 5 ns;
		rst <= '0'; wait for 5 ns;
		instr <= x"003100B3"; wait for 5 ns;
		instr <= x"00510093"; wait for 5 ns;
		wait;
	end process;
	process
	begin
		clk <= '0'; wait for 5 ns;
		clk <= '1'; wait for 5 ns;
	end process;
end architecture;

06_cpu/wave.vcd
$date
  Mon Mar 30 23:01:28 2026
$end
$version
  GHDL v0
$end
$timescale
  1 fs
$end
$scope module standard $end
$upscope $end
$scope module std_logic_1164 $end
$upscope $end
$scope module numeric_std $end
$upscope $end
$scope module tb_cpu_top $end
$var reg 1 ! clk $end
$var reg 1 " rst $end
$var reg 32 # instr[31:0] $end
$var reg 32 $ pc[31:0] $end
$scope module uut $end
$var reg 1 % clk $end
$var reg 1 & rst $end
$var reg 32 ' instr[31:0] $end
$var reg 32 ( pc[31:0] $end
$var reg 5 ) rs1_addr[4:0] $end
$var reg 5 * rs2_addr[4:0] $end
$var reg 5 + rd_addr[4:0] $end
$var reg 4 , alu_op[3:0] $end
$var reg 32 - imm[31:0] $end
$var reg 32 . alu_src_a[31:0] $end
$var reg 32 / alu_src_b[31:0] $end
$var reg 32 0 alu_result[31:0] $end
$var reg 32 1 rdata1[31:0] $end
$var reg 32 2 rdata2[31:0] $end
$var reg 1 3 reg_we $end
$var reg 1 4 mem_we $end
$var reg 1 5 zero $end
$var reg 32 6 pc_reg[31:0] $end
$scope module u_reg $end
$var reg 1 7 clk $end
$var reg 5 8 rs1[4:0] $end
$var reg 5 9 rs2[4:0] $end
$var reg 5 : rd[4:0] $end
$var reg 1 ; we $end
$var reg 32 < wdata[31:0] $end
$var reg 32 = rdata1[31:0] $end
$var reg 32 > rdata2[31:0] $end
$comment regs is not handled $end
$upscope $end
$scope module u_alu $end
$var reg 4 ? op[3:0] $end
$var reg 32 @ src_a[31:0] $end
$var reg 32 A src_b[31:0] $end
$var reg 32 B result[31:0] $end
$var reg 1 C zero $end
$var reg 32 D result_i[31:0] $end
$upscope $end
$scope module u_decoder $end
$var reg 32 E instr[31:0] $end
$var reg 5 F rs1[4:0] $end
$var reg 5 G rs2[4:0] $end
$var reg 5 H rd[4:0] $end
$var reg 32 I imm[31:0] $end
$var reg 4 J alu_op[3:0] $end
$var reg 1 K reg_we $end
$var reg 1 L mem_we $end
$var reg 7 M opcode[6:0] $end
$upscope $end
$upscope $end
$upscope $end
$enddefinitions $end
#0
0!
1"
bUUUUUUUUUUUUUUUUUUUUUUUUUUUUUUUU #
b00000000000000000000000000000000 $
0%
1&
bUUUUUUUUUUUUUUUUUUUUUUUUUUUUUUUU '
b00000000000000000000000000000000 (
bUUUUU )
bUUUUU *
bUUUUU +
b0000 ,
b00000000000000000000000000000000 -
b00000000000000000000000000000000 .
b00000000000000000000000000000000 /
b00000000000000000000000000000000 0
b00000000000000000000000000000000 1
b00000000000000000000000000000000 2
03
04
15
b00000000000000000000000000000000 6
07
bUUUUU 8
bUUUUU 9
bUUUUU :
0;
b00000000000000000000000000000000 <
b00000000000000000000000000000000 =
b00000000000000000000000000000000 >
b0000 ?
b00000000000000000000000000000000 @
b00000000000000000000000000000000 A
b00000000000000000000000000000000 B
1C
b00000000000000000000000000000000 D
bUUUUUUUUUUUUUUUUUUUUUUUUUUUUUUUU E
bUUUUU F
bUUUUU G
bUUUUU H
b00000000000000000000000000000000 I
b0000 J
0K
0L
bUUUUUUU M
#5000000
1!
0"
b00000000000000000000000000000100 $
1%
0&
b00000000000000000000000000000100 (
b00000000000000000000000000000100 6
17
#10000000
0!
b00000000001100010000000010110011 #
0%
b00000000001100010000000010110011 '
b00010 )
b00011 *
b00001 +
13
07
b00010 8
b00011 9
b00001 :
1;
b00000000001100010000000010110011 E
b00010 F
b00011 G
b00001 H
1K
b0110011 M
#15000000
1!
b00000000010100010000000010010011 #
b00000000000000000000000000001000 $
1%
b00000000010100010000000010010011 '
b00000000000000000000000000001000 (
b00101 *
b00000000000000000000000000000101 -
b00000000000000000000000000000101 /
b00000000000000000000000000000X0X 0
05
b00000000000000000000000000001000 6
17
b00101 9
b00000000000000000000000000000X0X <
b00000000000000000000000000000101 A
b00000000000000000000000000000X0X B
0C
b00000000000000000000000000000101 D
b00000000010100010000000010010011 E
b00101 G
b00000000000000000000000000000101 I
b0010011 M
#20000000
0!
0%
07
#25000000
1!
b00000000000000000000000000001100 $
1%
b00000000000000000000000000001100 (
b00000000000000000000000000001100 6
17
#30000000
0!
0%
07
#35000000
1!
b00000000000000000000000000010000 $
1%
b00000000000000000000000000010000 (
b00000000000000000000000000010000 6
17
#40000000
0!
0%
07
#45000000
1!
b00000000000000000000000000010100 $
1%
b00000000000000000000000000010100 (
b00000000000000000000000000010100 6
17
#50000000
0!
0%
07
#55000000
1!
b00000000000000000000000000011000 $
1%
b00000000000000000000000000011000 (
b00000000000000000000000000011000 6
17
#60000000
0!
0%
07
#65000000
1!
b00000000000000000000000000011100 $
1%
b00000000000000000000000000011100 (
b00000000000000000000000000011100 6
17
#70000000
0!
0%
07
#75000000
1!
b00000000000000000000000000100000 $
1%
b00000000000000000000000000100000 (
b00000000000000000000000000100000 6
17
#80000000
0!
0%
07
#85000000
1!
b00000000000000000000000000100100 $
1%
b00000000000000000000000000100100 (
b00000000000000000000000000100100 6
17
#90000000
0!
0%
07
#95000000
1!
b00000000000000000000000000101000 $
1%
b00000000000000000000000000101000 (
b00000000000000000000000000101000 6
17
#100000000
0!
0%
07
#105000000
1!
b00000000000000000000000000101100 $
1%
b00000000000000000000000000101100 (
b00000000000000000000000000101100 6
17
#110000000
0!
0%
07
#115000000
1!
b00000000000000000000000000110000 $
1%
b00000000000000000000000000110000 (
b00000000000000000000000000110000 6
17
#120000000
0!
0%
07
#125000000
1!
b00000000000000000000000000110100 $
1%
b00000000000000000000000000110100 (
b00000000000000000000000000110100 6
17
#130000000
0!
0%
07
#135000000
1!
b00000000000000000000000000111000 $
1%
b00000000000000000000000000111000 (
b00000000000000000000000000111000 6
17
#140000000
0!
0%
07
#145000000
1!
b00000000000000000000000000111100 $
1%
b00000000000000000000000000111100 (
b00000000000000000000000000111100 6
17
#150000000
0!
0%
07
#155000000
1!
b00000000000000000000000001000000 $
1%
b00000000000000000000000001000000 (
b00000000000000000000000001000000 6
17
#160000000
0!
0%
07
#165000000
1!
b00000000000000000000000001000100 $
1%
b00000000000000000000000001000100 (
b00000000000000000000000001000100 6
17
#170000000
0!
0%
07
#175000000
1!
b00000000000000000000000001001000 $
1%
b00000000000000000000000001001000 (
b00000000000000000000000001001000 6
17
#180000000
0!
0%
07
#185000000
1!
b00000000000000000000000001001100 $
1%
b00000000000000000000000001001100 (
b00000000000000000000000001001100 6
17
#190000000
0!
0%
07
#195000000
1!
b00000000000000000000000001010000 $
1%
b00000000000000000000000001010000 (
b00000000000000000000000001010000 6
17
